PyDAX/DAXExpression.py
PyDAX/PyDAXLexer.py
PyDAX/__init__.py
pydaxlexer-0.1.5.dist-info/licenses/LICENSE
pydaxlexer-0.1.5.dist-info/METADATA
pydaxlexer-0.1.5.dist-info/WHEEL
pydaxlexer-0.1.5.dist-info/top_level.txt
pydaxlexer-0.1.5.dist-info/RECORD
