Metadata-Version: 2.4
Name: PyDAXLexer
Version: 0.1.5
Summary: PyDAX is designed to analyze DAX, it can extract comments, remove comments, and identify columns and measures referenced in DAX expressions.
Author-email: Klaus Jürgen Folz <klausjurgenfolz@gmail.com>
Project-URL: Linkedin, https://www.linkedin.com/in/klausjfolz/
Project-URL: GitHub, https://github.com/jurgenfolz/PyDAXLexer
Classifier: Programming Language :: Python :: 3
Classifier: License :: OSI Approved :: MIT License
Classifier: Operating System :: OS Independent
Requires-Python: >=3.10
License-File: LICENSE
Requires-Dist: antlr4-python3-runtime==4.13.2
Dynamic: license-file
